images/bladerunner_olive.jpg
images/candles.jpg
images/dance.jpg
images/great_wave.jpg
images/neighborhood_succulents.jpg
images/pink_roses.jpg
images/pink_roses_full_res.jpg
images/red_roses.jpg
images/sunset.jpg
images/vangogh.bmp
images/vangogh.gif
images/vangogh.jpg
images/vangogh.png
images/vangogh.tiff
images/vangogh_small.png
images/water.jpg
palettecleanse/__init__.py
palettecleanse/custom.py
palettecleanse/palette.py
palettecleanse/palettes.py
palettecleanse/presets.py
palettecleanse/utils.py
tests/__init__.py
tests/test_palette.py
tests/test_presets.py
palettecleanse-2.0.0.dist-info/LICENSE.txt
palettecleanse-2.0.0.dist-info/METADATA
palettecleanse-2.0.0.dist-info/WHEEL
palettecleanse-2.0.0.dist-info/top_level.txt
palettecleanse-2.0.0.dist-info/RECORD
