Metadata-Version: 2.1
Name: palettecleanse
Version: 2.0.0
Summary: palettecleanse is a python library for quick conversions of images to custom color palettes
Author-email: Jiaming Chen <jiaming.justin.chen@gmail.com>
Maintainer-email: Jiaming Chen <jiaming.justin.chen@gmail.com>
License: The MIT License (MIT)
Project-URL: Homepage, https://github.com/sansona/palettecleanse
Project-URL: Issues, https://github.com/sansona/palettecleanse/issues
Keywords: matplotlib,seaborn,plotly,data visualization,color map,color palette,palette
Requires-Python: >=3.8
License-File: LICENSE.txt
